cheroot/__init__.py
cheroot/__init__.pyi
cheroot/__main__.py
cheroot/_compat.py
cheroot/_compat.pyi
cheroot/cli.py
cheroot/cli.pyi
cheroot/connections.py
cheroot/connections.pyi
cheroot/errors.py
cheroot/errors.pyi
cheroot/makefile.py
cheroot/makefile.pyi
cheroot/py.typed
cheroot/server.py
cheroot/server.pyi
cheroot/testing.py
cheroot/testing.pyi
cheroot/wsgi.py
cheroot/wsgi.pyi
cheroot/ssl/__init__.py
cheroot/ssl/__init__.pyi
cheroot/ssl/builtin.py
cheroot/ssl/builtin.pyi
cheroot/ssl/pyopenssl.py
cheroot/ssl/pyopenssl.pyi
cheroot/test/__init__.py
cheroot/test/_pytest_plugin.py
cheroot/test/conftest.py
cheroot/test/helper.py
cheroot/test/test__compat.py
cheroot/test/test_cli.py
cheroot/test/test_conn.py
cheroot/test/test_core.py
cheroot/test/test_dispatch.py
cheroot/test/test_errors.py
cheroot/test/test_makefile.py
cheroot/test/test_server.py
cheroot/test/test_ssl.py
cheroot/test/test_wsgi.py
cheroot/test/webtest.py
cheroot/workers/__init__.py
cheroot/workers/__init__.pyi
cheroot/workers/threadpool.py
cheroot/workers/threadpool.pyi
cheroot-11.1.1.dist-info/LICENSE.md
cheroot-11.1.1.dist-info/METADATA
cheroot-11.1.1.dist-info/WHEEL
cheroot-11.1.1.dist-info/entry_points.txt
cheroot-11.1.1.dist-info/top_level.txt
cheroot-11.1.1.dist-info/RECORD
