Metadata-Version: 2.1
Name: cheroot
Version: 11.1.1
Summary: Highly-optimized, pure-python HTTP server
Author-email: CherryPy Team <team@cherrypy.dev>
Project-URL: Homepage, https://cheroot.cherrypy.dev
Project-URL: Chat: Matrix, https://matrix.to/#/#cherrypy-space:matrix.org
Project-URL: CI: GitHub, https://github.com/cherrypy/cheroot/actions
Project-URL: Docs: RTD, https://cheroot.cherrypy.dev
Project-URL: GitHub: issues, https://github.com/cherrypy/cheroot/issues
Project-URL: GitHub: repo, https://github.com/cherrypy/cheroot
Project-URL: Tidelift: funding, https://tidelift.com/subscription/pkg/pypi-cheroot?utm_source=pypi-cheroot&utm_medium=referral&utm_campaign=pypi
Keywords: http,server,ssl,wsgi
Classifier: Development Status :: 5 - Production/Stable
Classifier: Environment :: Web Environment
Classifier: Intended Audience :: Developers
Classifier: Operating System :: OS Independent
Classifier: Framework :: CherryPy
Classifier: License :: OSI Approved :: BSD License
Classifier: Programming Language :: Python
Classifier: Programming Language :: Python :: 3
Classifier: Programming Language :: Python :: 3 :: Only
Classifier: Programming Language :: Python :: 3.8
Classifier: Programming Language :: Python :: 3.9
Classifier: Programming Language :: Python :: 3.10
Classifier: Programming Language :: Python :: 3.11
Classifier: Programming Language :: Python :: 3.12
Classifier: Programming Language :: Python :: 3.13
Classifier: Programming Language :: Python :: Implementation
Classifier: Programming Language :: Python :: Implementation :: CPython
Classifier: Programming Language :: Python :: Implementation :: Jython
Classifier: Programming Language :: Python :: Implementation :: PyPy
Classifier: Topic :: Internet :: WWW/HTTP
Classifier: Topic :: Internet :: WWW/HTTP :: HTTP Servers
Classifier: Topic :: Internet :: WWW/HTTP :: WSGI
Classifier: Topic :: Internet :: WWW/HTTP :: WSGI :: Server
Classifier: Typing :: Typed
Requires-Python: >=3.8
License-File: LICENSE.md
Requires-Dist: more_itertools>=2.6
Requires-Dist: jaraco.functools
Provides-Extra: docs
Requires-Dist: sphinx>=1.8.2; extra == "docs"
Requires-Dist: jaraco.packaging>=3.2; extra == "docs"
Requires-Dist: sphinx-tabs>=1.1.0; extra == "docs"
Requires-Dist: furo; extra == "docs"
Requires-Dist: python-dateutil; extra == "docs"
Requires-Dist: sphinxcontrib-apidoc>=0.3.0; extra == "docs"
